taggit_machinetags/__init__.py
taggit_machinetags/fields.py
taggit_machinetags/managers.py
taggit_machinetags/models.py
taggit_machinetags/tests.py
taggit_machinetags/migrations/0001_initial.py
taggit_machinetags/migrations/0002_auto_20201012_1308.py
taggit_machinetags/migrations/__init__.py
taggit_machinetags/south_migrations/0001_initial.py
taggit_machinetags/south_migrations/__init__.py
test_project/__init__.py
test_project/settings.py
test_project/urls.py
test_project/wsgi.py
django_taggit_machinetags-1.0.0.dist-info/LICENSE
django_taggit_machinetags-1.0.0.dist-info/METADATA
django_taggit_machinetags-1.0.0.dist-info/WHEEL
django_taggit_machinetags-1.0.0.dist-info/top_level.txt
django_taggit_machinetags-1.0.0.dist-info/RECORD
