Metadata-Version: 2.1
Name: django-taggit-machinetags
Version: 1.0.0
Summary: Machine tagging built upon django-taggit
Home-page: http://github.com/lpomfrey/django-taggit-machinetags
Author: Luke Pomfrey
Author-email: django-taggitmachinetags@lukepomfrey.org
Maintainer: Luke Pomfrey
Maintainer-email: django-taggitmachinetags@lukepomfrey.org
License: BSD
Platform: UNKNOWN
Classifier: Development Status :: 4 - Beta
Classifier: Environment :: Web Environment
Classifier: Intended Audience :: Developers
Classifier: License :: OSI Approved :: BSD License
Classifier: Operating System :: OS Independent
Classifier: Framework :: Django
Classifier: Framework :: Django :: 2.2
Classifier: Framework :: Django :: 3.0
Classifier: Framework :: Django :: 3.1
Classifier: Programming Language :: Python
Classifier: Programming Language :: Python :: 3
Classifier: Programming Language :: Python :: 3.6
Classifier: Programming Language :: Python :: 3.7
Classifier: Programming Language :: Python :: 3.8
Classifier: Programming Language :: Python :: Implementation :: CPython
Classifier: Programming Language :: Python :: Implementation :: PyPy
Requires-Python: >=3.6
Requires-Dist: django-taggit (>=1.0.0)
